sysu_health_indices/__init__.py
sysu_health_indices/sysu_health_indices.py
sysu_health_indices-0.1.0.dist-info/METADATA
sysu_health_indices-0.1.0.dist-info/WHEEL
sysu_health_indices-0.1.0.dist-info/RECORD
